z3c/password/DEPENDENCIES.txt
z3c/password/README.txt
z3c/password/__init__.py
z3c/password/configure.zcml
z3c/password/field.py
z3c/password/interfaces.py
z3c/password/password.py
z3c/password/principal.py
z3c/password/principal.txt
z3c/password/testing.py
z3c/password/tests.py
z3c/password/z3c.password-configure.zcml
z3c/password/locales/z3c.password.pot
z3c/password/locales/de/LC_MESSAGES/z3c.password.mo
z3c/password/locales/de/LC_MESSAGES/z3c.password.po
z3c/password/locales/nl/LC_MESSAGES/z3c.password.mo
z3c/password/locales/nl/LC_MESSAGES/z3c.password.po
z3c/password/locales/ru/LC_MESSAGES/z3c.password.mo
z3c/password/locales/ru/LC_MESSAGES/z3c.password.po
z3c_password-3.0.dist-info/LICENSE.txt
z3c_password-3.0.dist-info/METADATA
z3c_password-3.0.dist-info/WHEEL
z3c_password-3.0.dist-info/top_level.txt
z3c_password-3.0.dist-info/RECORD
