Metadata-Version: 2.2
Name: z3c.password
Version: 3.0
Summary: Password generation and verification utility for Zope3
Home-page: https://github.com/zopefoundation/z3c.password
Author: Stephan Richter, Roger Ineichen and the Zope Community
Author-email: zope-dev@zope.dev
License: ZPL-2.1
Keywords: zope3 z3c password verification
Classifier: Development Status :: 5 - Production/Stable
Classifier: Environment :: Web Environment
Classifier: Intended Audience :: Developers
Classifier: License :: OSI Approved :: Zope Public License
Classifier: Programming Language :: Python
Classifier: Programming Language :: Python :: 3
Classifier: Programming Language :: Python :: 3.9
Classifier: Programming Language :: Python :: 3.10
Classifier: Programming Language :: Python :: 3.11
Classifier: Programming Language :: Python :: 3.12
Classifier: Programming Language :: Python :: 3.13
Classifier: Programming Language :: Python :: Implementation :: CPython
Classifier: Programming Language :: Python :: Implementation :: PyPy
Classifier: Natural Language :: English
Classifier: Operating System :: OS Independent
Classifier: Topic :: Internet :: WWW/HTTP
Classifier: Framework :: Zope :: 3
Requires-Python: >=3.9
License-File: LICENSE.txt
Requires-Dist: setuptools
Requires-Dist: zope.component
Requires-Dist: zope.exceptions
Requires-Dist: zope.i18nmessageid
Requires-Dist: zope.i18n
Requires-Dist: zope.interface
Requires-Dist: zope.schema
Requires-Dist: zope.security
Provides-Extra: test
Requires-Dist: z3c.coverage; extra == "test"
Requires-Dist: zope.password; extra == "test"
Requires-Dist: zope.pluggableauth; extra == "test"
Requires-Dist: zope.testing; extra == "test"
Dynamic: author
Dynamic: author-email
Dynamic: classifier
Dynamic: description
Dynamic: home-page
Dynamic: keywords
Dynamic: license
Dynamic: provides-extra
Dynamic: requires-dist
Dynamic: requires-python
Dynamic: summary
